traxis/__init__.py
traxis/__main__.py
traxis/constants.py
traxis/calc/__init__.py
traxis/calc/anglecalc.py
traxis/calc/circlefit.py
traxis/calc/optdensity.py
traxis/graphics/__init__.py
traxis/graphics/angleref.py
traxis/graphics/fittedarc.py
traxis/graphics/markers.py
traxis/graphics/tangent.py
traxis/gui/__init__.py
traxis/gui/maingui.py
traxis/gui/mainwindow.py
traxis/gui/skeleton.py
traxis-1.2.0.data/scripts/runtraxis
traxis-1.2.0.dist-info/LICENSE
traxis-1.2.0.dist-info/METADATA
traxis-1.2.0.dist-info/WHEEL
traxis-1.2.0.dist-info/entry_points.txt
traxis-1.2.0.dist-info/top_level.txt
traxis-1.2.0.dist-info/RECORD
