Metadata-Version: 2.1
Name: traxis
Version: 1.2.0
Summary: An application to measure bubble-chamber images for the UofT advanced physics lab.
Home-page: https://gitlab.physics.utoronto.ca/advanced-lab/traxis
Author: Syed Haider Abidi, Nooruddin Ahmed, Christopher Dydul
Maintainer: John Ladan
Maintainer-email: jladan@physics.utoronto.ca
License: GPL3
License-File: LICENSE
Requires-Dist: numpy
Requires-Dist: scipy
Requires-Dist: PyQt5
